mlauto/__init__.py
mlauto/mlauto.py
mlauto-3.0.37.dist-info/METADATA
mlauto-3.0.37.dist-info/WHEEL
mlauto-3.0.37.dist-info/top_level.txt
mlauto-3.0.37.dist-info/RECORD
