Metadata-Version: 2.1
Name: mlauto
Version: 3.0.37
Summary: UNKNOWN
Home-page: https://github.com/ansariminhaj/mlauto_pip
Author: Minhaj Ansari
License: MIT
Platform: UNKNOWN
Classifier: Intended Audience :: Science/Research
Classifier: Programming Language :: Python :: 3
Requires-Dist: numpy
Requires-Dist: GPUtil
Requires-Dist: psutil
